pyiron_dataclasses/__init__.py
pyiron_dataclasses/_version.py
pyiron_dataclasses/v1/__init__.py
pyiron_dataclasses/v1/converter.py
pyiron_dataclasses/v1/shared.py
pyiron_dataclasses/v1/jobs/__init__.py
pyiron_dataclasses/v1/jobs/atomistic.py
pyiron_dataclasses/v1/jobs/dft.py
pyiron_dataclasses/v1/jobs/generic.py
pyiron_dataclasses/v1/jobs/lammps.py
pyiron_dataclasses/v1/jobs/murn.py
pyiron_dataclasses/v1/jobs/sphinx.py
pyiron_dataclasses/v1/jobs/vasp.py
pyiron_dataclasses-0.0.10.dist-info/METADATA
pyiron_dataclasses-0.0.10.dist-info/WHEEL
pyiron_dataclasses-0.0.10.dist-info/licenses/LICENSE
pyiron_dataclasses-0.0.10.dist-info/RECORD
