Metadata-Version: 2.4
Name: pyiron_dataclasses
Version: 0.0.10
Summary: Dataclasses for the pyiron workflow framework
Project-URL: Homepage, https://github.com/pyiron/pyiron_dataclasses
Project-URL: Documentation, https://github.com/pyiron/pyiron_dataclasses
Project-URL: Repository, https://github.com/pyiron/pyiron_dataclasses
Author-email: Jan Janssen <janssen@mpie.de>
License: BSD 3-Clause License
License-File: LICENSE
Keywords: pyiron
Classifier: Development Status :: 5 - Production/Stable
Classifier: Intended Audience :: Science/Research
Classifier: License :: OSI Approved :: BSD License
Classifier: Operating System :: OS Independent
Classifier: Programming Language :: Python :: 3.10
Classifier: Programming Language :: Python :: 3.11
Classifier: Programming Language :: Python :: 3.12
Classifier: Programming Language :: Python :: 3.13
Classifier: Programming Language :: Python :: 3.14
Classifier: Topic :: Scientific/Engineering :: Physics
Requires-Python: <3.15,>=3.9
Requires-Dist: numpy<=2.4.1,>=1.23.5
Requires-Dist: pint<=0.25.2,>=0.18
Provides-Extra: convert
Requires-Dist: h5io-browser<=0.2.2,>=0.1.2; extra == 'convert'
